license_tools/__init__.py
license_tools/__main__.py
license_tools/constants.py
license_tools/py.typed
license_tools/retrieval.py
license_tools/tools/__init__.py
license_tools/tools/cargo_tools.py
license_tools/tools/font_tools.py
license_tools/tools/image_tools.py
license_tools/tools/linking_tools.py
license_tools/tools/pip_tools.py
license_tools/tools/rpm_tools.py
license_tools/tools/scancode_tools.py
license_tools/tools/translation_tools.py
license_tools/utils/__init__.py
license_tools/utils/archive_utils.py
license_tools/utils/download_utils.py
license_tools/utils/path_utils.py
license_tools/utils/rendering_utils.py
license_tools-0.17.0.dist-info/licenses/LICENSE.txt
license_tools-0.17.0.dist-info/METADATA
license_tools-0.17.0.dist-info/WHEEL
license_tools-0.17.0.dist-info/top_level.txt
license_tools-0.17.0.dist-info/RECORD
