Metadata-Version: 2.4
Name: license_tools
Version: 0.17.0
Summary: Collection of tools for working with Open Source licenses
Author: stefan6419846
License-Expression: Apache-2.0
Project-URL: Homepage, https://github.com/stefan6419846/license_tools
Project-URL: Documentation, https://license-tools.readthedocs.io/
Project-URL: Repository, https://github.com/stefan6419846/license_tools
Project-URL: Issues, https://github.com/stefan6419846/license_tools/issues
Project-URL: Changelog, https://github.com/stefan6419846/license_tools/blob/main/CHANGELOG.md
Keywords: open source,license,package,dependency,licensing
Classifier: Development Status :: 4 - Beta
Classifier: Environment :: Console
Classifier: Intended Audience :: Developers
Classifier: Programming Language :: Python :: 3
Classifier: Programming Language :: Python :: 3 :: Only
Classifier: Topic :: Software Development
Classifier: Topic :: Utilities
Classifier: Typing :: Typed
Requires-Python: <4,>=3.9
License-File: LICENSE.txt
Requires-Dist: scancode-toolkit>=32.3.0
Requires-Dist: typecode-libmagic
Requires-Dist: joblib
Requires-Dist: eot-tools
Requires-Dist: fontTools[woff]
Requires-Dist: pip-licenses-lib>=0.4.0
Requires-Dist: requests
Requires-Dist: tomli
Provides-Extra: dev
Requires-Dist: codespell; extra == "dev"
Requires-Dist: coverage; extra == "dev"
Requires-Dist: faker; extra == "dev"
Requires-Dist: flake8; extra == "dev"
Requires-Dist: flake8-bugbear; extra == "dev"
Requires-Dist: pep8-naming; extra == "dev"
Requires-Dist: mypy; extra == "dev"
Requires-Dist: types-requests; extra == "dev"
Provides-Extra: extended-rpm
Requires-Dist: rpmfile>=2.1.0; extra == "extended-rpm"
Provides-Extra: docs
Requires-Dist: sphinx; extra == "docs"
Requires-Dist: furo; extra == "docs"
Dynamic: license-file
